wagtail_easy_thumbnails/__init__.py
wagtail_easy_thumbnails/processors.py
wagtail_easy_thumbnails/settings.py
wagtail_easy_thumbnails/utils.py
wagtail_easy_thumbnails/templatetags/__init__.py
wagtail_easy_thumbnails/templatetags/wagtail_thumbnail.py
wagtail_easy_thumbnails-0.3.dist-info/DESCRIPTION.rst
wagtail_easy_thumbnails-0.3.dist-info/METADATA
wagtail_easy_thumbnails-0.3.dist-info/RECORD
wagtail_easy_thumbnails-0.3.dist-info/WHEEL
wagtail_easy_thumbnails-0.3.dist-info/metadata.json
wagtail_easy_thumbnails-0.3.dist-info/top_level.txt
