Metadata-Version: 2.0
Name: wagtail-easy-thumbnails
Version: 0.3
Summary: Use easy_thumbnails with Django Wagtail images
Home-page: https://github.com/fabrique/wagtail-easy-thumbnails
Author: Robin van der Rijst - Fabrique
Author-email: robinr@fabrique.nl
License: MIT
Platform: UNKNOWN
Classifier: Environment :: Web Environment
Classifier: Framework :: Django
Classifier: Intended Audience :: Developers
Classifier: License :: OSI Approved :: MIT License
Classifier: Operating System :: OS Independent
Classifier: Programming Language :: Python
Classifier: Programming Language :: Python :: 3
Classifier: Programming Language :: Python :: 3.3
Classifier: Programming Language :: Python :: 3.4
Classifier: Programming Language :: Python :: 3.5
Classifier: Topic :: Software Development :: Libraries :: Application Frameworks
Classifier: Topic :: Software Development :: Libraries :: Python Modules
Requires-Dist: easy-thumbnails (>=2.3)
Requires-Dist: wagtail (>=1.5)
